README.rst
setup.py
aioprometheus_binary_format/__init__.py
aioprometheus_binary_format/binary.py
aioprometheus_binary_format.egg-info/PKG-INFO
aioprometheus_binary_format.egg-info/SOURCES.txt
aioprometheus_binary_format.egg-info/dependency_links.txt
aioprometheus_binary_format.egg-info/requires.txt
aioprometheus_binary_format.egg-info/top_level.txt