Metadata-Version: 1.0
Name: aioprometheus-binary-format
Version: 1.0.0
Summary: This package provides binary metrics format support for aioprometheus
Home-page: https://github.com/claws/aioprometheus-binary-format
Author: Chris Laws
Author-email: clawsicus@gmail.com
License: MIT
Keywords: prometheus,monitoring,metrics
Platform: UNKNOWN
